MyNoSQL/MyNoSQL.py
MyNoSQL/__init__.py
MyNoSQL-0.0.6.dist-info/LICENSE
MyNoSQL-0.0.6.dist-info/METADATA
MyNoSQL-0.0.6.dist-info/WHEEL
MyNoSQL-0.0.6.dist-info/top_level.txt
MyNoSQL-0.0.6.dist-info/RECORD
