Metadata-Version: 2.1
Name: MyNoSQL
Version: 0.0.6
Summary: MyNoSQL
Home-page: https://github.com/damies13/mynosql
Author: damies13
Author-email: damies13+mynosql@gmail.com
License: UNKNOWN
Project-URL: Getting Help, https://github.com/damies13/mynosql
Project-URL: Source, https://github.com/damies13/mynosql
Platform: UNKNOWN
Classifier: Development Status :: 3 - Alpha
Classifier: Topic :: Database :: Database Engines/Servers
Classifier: Programming Language :: Python :: 3.8
Classifier: License :: OSI Approved :: GNU General Public License v2 (GPLv2)
Classifier: Operating System :: OS Independent
Requires-Python: >=3.8
License-File: LICENSE
Requires-Dist: requests
Requires-Dist: HTTPServer
